README.rst
setup.py
pushscreeps/__init__.py
pushscreeps/pushscreeps.py
pushscreeps.egg-info/PKG-INFO
pushscreeps.egg-info/SOURCES.txt
pushscreeps.egg-info/dependency_links.txt
pushscreeps.egg-info/entry_points.txt
pushscreeps.egg-info/requires.txt
pushscreeps.egg-info/top_level.txt