Metadata-Version: 1.0
Name: pushscreeps
Version: 0.1.2
Summary: Python3 script for pushing code to screeps
Home-page: https://github.com/mboehn/pushscreeps
Author: Mathias Bøhn Grytemark
Author-email: mathias@grytemark.no
License: UNKNOWN
Platform: UNKNOWN
